livekit_evals/__init__.py
livekit_evals/config.py
livekit_evals/recording_manager.py
livekit_evals/webhook_handler.py
livekit_evals-0.1.7.dist-info/licenses/LICENSE
livekit_evals-0.1.7.dist-info/METADATA
livekit_evals-0.1.7.dist-info/WHEEL
livekit_evals-0.1.7.dist-info/top_level.txt
livekit_evals-0.1.7.dist-info/RECORD
