Metadata-Version: 2.4
Name: livekit-evals
Version: 0.1.7
Summary: Track and evaluate LiveKit agent sessions with automatic metrics, transcripts, and usage analytics
Author-email: superbryndev <support@superbryndev.com>
License: MIT
Project-URL: Homepage, https://github.com/superbryndev/livekit-evals
Project-URL: Documentation, https://github.com/superbryndev/livekit-evals#readme
Project-URL: Repository, https://github.com/superbryndev/livekit-evals
Project-URL: Issues, https://github.com/superbryndev/livekit-evals/issues
Keywords: livekit,agents,analytics,metrics,evaluation,voice-ai
Classifier: Development Status :: 4 - Beta
Classifier: Intended Audience :: Developers
Classifier: License :: OSI Approved :: MIT License
Classifier: Programming Language :: Python :: 3
Classifier: Programming Language :: Python :: 3.9
Classifier: Programming Language :: Python :: 3.10
Classifier: Programming Language :: Python :: 3.11
Classifier: Programming Language :: Python :: 3.12
Classifier: Topic :: Software Development :: Libraries :: Python Modules
Classifier: Topic :: Communications :: Telephony
Classifier: Topic :: Multimedia :: Sound/Audio :: Speech
Requires-Python: >=3.9
License-File: LICENSE
Requires-Dist: livekit-agents>=0.8.0
Requires-Dist: aiohttp>=3.9.0
Dynamic: license-file
